NoteBin/__init__.py
NoteBin/notetaker.py
NoteBin-0.0.4.dist-info/METADATA
NoteBin-0.0.4.dist-info/WHEEL
NoteBin-0.0.4.dist-info/top_level.txt
NoteBin-0.0.4.dist-info/RECORD
